{
  "BraveRewardsDisabled": true,
  "BraveWalletDisabled": true,
  "BraveVPNDisabled": true,
  "BraveTalkDisabled": true,
  "BraveAIChatEnabled": false,
  "TorDisabled": true,

  "MetricsReportingEnabled": false,
  "SafeBrowsingProtectionLevel": 0,
  "SpellCheckServiceEnabled": false,

  "SyncDisabled": false,

  "BuiltInDnsClientEnabled": false,
  "DnsOverHttpsMode": "automatic",
  "NetworkPredictionOptions": 2,

  "ShowHomeButton": false,
  "BookmarkBarEnabled": false,
  "NewTabPageLocation": "https://duckduckgo.com/"
}
